<?xml version="1.0" encoding="utf-8" ?>
<dwsync>
<file name="jquery.js" local="128334823592527500" remote="128334821100000000" testing="0" />
<file name="jqModal.js" local="128257752323191250" remote="128257752200000000" testing="0" />
<file name="jqDnR.js" local="128260521780625000" remote="128260518160000000" testing="0" />
<file name="jquery.form.js" local="128334818609558750" remote="128334816800000000" testing="0" />
<file name="autohelp.js" local="128257736002722500" remote="128257735020000000" testing="0" />
<file name="jquery-1.1.2.pack.js" local="128257722134285000" remote="128257717840000000" testing="0" />
<file name="jquery-modalContent.packed.js" local="128257755963503750" remote="128257752200000000" testing="0" />
<file name="thickbox-compressed.js" local="128257731587097500" remote="128257730730000000" testing="0" />
<file name="jquery.corner.js" local="128306038190313750" remote="128306036220000000" testing="0" />
<file name="progress.js" local="128334778661746250" remote="128334778150000000" testing="0" />
<file name="jBox.js" local="128340680654012500" remote="128340679430000000" testing="0" />
</dwsync>